wspyserial/__init__.py
wspyserial/__main__.py
wspyserial/client.py
wspyserial/config.toml
wspyserial/device.py
wspyserial/gcode.py
wspyserial/protocol.py
wspyserial/server.py
wspyserial-1.1.0.dist-info/LICENSE
wspyserial-1.1.0.dist-info/METADATA
wspyserial-1.1.0.dist-info/WHEEL
wspyserial-1.1.0.dist-info/entry_points.txt
wspyserial-1.1.0.dist-info/top_level.txt
wspyserial-1.1.0.dist-info/RECORD
